dolfin_adjoint/__init__.py
dolfin_adjoint-2025.0.0.dist-info/licenses/LICENSE
fenics_adjoint/__init__.py
fenics_adjoint/assembly.py
fenics_adjoint/interpolation.py
fenics_adjoint/krylov_solver.py
fenics_adjoint/lu_solver.py
fenics_adjoint/newton_solver.py
fenics_adjoint/petsc_krylov_solver.py
fenics_adjoint/projection.py
fenics_adjoint/refine.py
fenics_adjoint/shapead_transformations.py
fenics_adjoint/solving.py
fenics_adjoint/system_assembly.py
fenics_adjoint/ufl_constraints.py
fenics_adjoint/utils.py
fenics_adjoint/variational_solver.py
fenics_adjoint/blocks/__init__.py
fenics_adjoint/blocks/assembly.py
fenics_adjoint/blocks/constant.py
fenics_adjoint/blocks/dirichlet_bc.py
fenics_adjoint/blocks/function.py
fenics_adjoint/blocks/function_assigner.py
fenics_adjoint/blocks/krylov_solver.py
fenics_adjoint/blocks/lu_solver.py
fenics_adjoint/blocks/petsc_krylov_solver.py
fenics_adjoint/blocks/projection.py
fenics_adjoint/blocks/solving.py
fenics_adjoint/blocks/variational_solver.py
fenics_adjoint/types/__init__.py
fenics_adjoint/types/as_backend_type.py
fenics_adjoint/types/constant.py
fenics_adjoint/types/dirichletbc.py
fenics_adjoint/types/expression.py
fenics_adjoint/types/function.py
fenics_adjoint/types/function_assigner.py
fenics_adjoint/types/function_space.py
fenics_adjoint/types/genericmatrix.py
fenics_adjoint/types/genericvector.py
fenics_adjoint/types/io.py
fenics_adjoint/types/mesh.py
dolfin_adjoint-2025.0.0.dist-info/METADATA
dolfin_adjoint-2025.0.0.dist-info/WHEEL
dolfin_adjoint-2025.0.0.dist-info/top_level.txt
dolfin_adjoint-2025.0.0.dist-info/RECORD
