Metadata-Version: 2.4
Name: dolfin_adjoint
Version: 2025.0.0
Summary: High-level automatic differentiation library for FEniCS
Author: Jørgen S. Dokken, Sebastian K. Mitusch, Simon W. Funke
License:                    GNU LESSER GENERAL PUBLIC LICENSE
License-File: LICENSE
Requires-Dist: fenics-ufl-legacy
Requires-Dist: scipy>=1.0
Requires-Dist: pyadjoint-ad
Requires-Dist: numpy<2.0.0
Provides-Extra: moola
Requires-Dist: moola>=0.1.6; extra == "moola"
Provides-Extra: test
Requires-Dist: pytest>=3.10; extra == "test"
Requires-Dist: flake8; extra == "test"
Requires-Dist: coverage; extra == "test"
Provides-Extra: dev
Requires-Dist: pdbpp; extra == "dev"
Requires-Dist: ipython; extra == "dev"
Requires-Dist: mypy; extra == "dev"
Requires-Dist: flake8; extra == "dev"
Provides-Extra: visualisation
Requires-Dist: tensorflow; extra == "visualisation"
Requires-Dist: protobuf; extra == "visualisation"
Requires-Dist: networkx; extra == "visualisation"
Requires-Dist: pygraphviz; extra == "visualisation"
Provides-Extra: meshing
Requires-Dist: pygmsh; extra == "meshing"
Requires-Dist: meshio; extra == "meshing"
Provides-Extra: doc
Requires-Dist: sphinx; extra == "doc"
Requires-Dist: sphinx-autobuild; extra == "doc"
Requires-Dist: sphinxcontrib-bibtex; extra == "doc"
Requires-Dist: pylit; extra == "doc"
Requires-Dist: sphinxcontrib-youtube; extra == "doc"
Provides-Extra: all
Requires-Dist: dolfin_adjoint[test]; extra == "all"
Requires-Dist: dolfin_adjoint[moola]; extra == "all"
Requires-Dist: dolfin_adjoint[dev]; extra == "all"
Requires-Dist: dolfin_adjoint[visualisation]; extra == "all"
Requires-Dist: dolfin_adjoint[doc]; extra == "all"
Dynamic: license-file
